apisinda/__init__.py
apisinda/pcds.py
apisinda/session.py
apisinda-1.0.1.dist-info/LICENSE
apisinda-1.0.1.dist-info/METADATA
apisinda-1.0.1.dist-info/WHEEL
apisinda-1.0.1.dist-info/top_level.txt
apisinda-1.0.1.dist-info/RECORD
