Metadata-Version: 2.1
Name: apisinda
Version: 1.0.1
Summary: SINDA API
Author-email: Alessandro Cerioli <ceriolialessandro98@gmail.com>
License: MIT License
Project-URL: repository, https://github.com
Classifier: License :: OSI Approved :: MIT License
Classifier: Programming Language :: Python :: 3
Requires-Python: >=3.7
License-File: LICENSE
Requires-Dist: requests
Requires-Dist: pandas
Provides-Extra: build
Requires-Dist: build ; extra == 'build'
Requires-Dist: twine ; extra == 'build'
